iotlab_mqtt_bridge/__init__.py
iotlab_mqtt_bridge/__main__.py
iotlab_mqtt_bridge/helpers.py
iotlab_mqtt_bridge/iotlab_mqtt_bridge.py
iotlab_mqtt_bridge-0.1.21.dist-info/LICENSE
iotlab_mqtt_bridge-0.1.21.dist-info/METADATA
iotlab_mqtt_bridge-0.1.21.dist-info/WHEEL
iotlab_mqtt_bridge-0.1.21.dist-info/top_level.txt
iotlab_mqtt_bridge-0.1.21.dist-info/RECORD
