Metadata-Version: 2.1
Name: iotlab-mqtt-bridge
Version: 0.1.21
Summary: Bridge to connect IOT-LAB to a MQTT broker
Home-page: https://gitlab.irit.fr/rmess/locura/infra/iotlab_mqtt_bridge
Author: Cassandre Vey
Author-email: cassandre.vey@irit.fr
License: CeCILL 2.1
Classifier: Development Status :: 1 - Planning
Classifier: Intended Audience :: Science/Research
Classifier: Operating System :: POSIX :: Linux
Classifier: Programming Language :: Python :: 3
License-File: LICENSE
Requires-Dist: iotlabcli (>=3.3.0)
Requires-Dist: paho-mqtt
